nanome_minimization/Minimization.py
nanome_minimization/_MinimizationMenu.json
nanome_minimization/_MinimizationMenu.py
nanome_minimization/_MinimizationProcess.py
nanome_minimization/__init__.py
nanome_minimization-0.3.0.dist-info/LICENSE
nanome_minimization-0.3.0.dist-info/METADATA
nanome_minimization-0.3.0.dist-info/WHEEL
nanome_minimization-0.3.0.dist-info/entry_points.txt
nanome_minimization-0.3.0.dist-info/top_level.txt
nanome_minimization-0.3.0.dist-info/RECORD
