Metadata-Version: 2.1
Name: nanome-minimization
Version: 0.3.0
Summary: Nanome Plugin to run minimization on selected structures
Home-page: https://github.com/nanome-ai/plugin-minimization
Author: Nanome
Author-email: hello@nanome.ai
License: MIT
Keywords: virtual-reality,chemistry,python,api,plugin
Platform: any
Classifier: Development Status :: 3 - Alpha
Classifier: Intended Audience :: Science/Research
Classifier: Topic :: Scientific/Engineering :: Chemistry
Classifier: License :: OSI Approved :: MIT License
Classifier: Programming Language :: Python :: 2.7
Classifier: Programming Language :: Python :: 3.5
Classifier: Programming Language :: Python :: 3.6
Classifier: Programming Language :: Python :: 3.7
Requires-Dist: nanome
